pylor/__init__.py
pylor-0.0.2.dist-info/LICENSE
pylor-0.0.2.dist-info/METADATA
pylor-0.0.2.dist-info/WHEEL
pylor-0.0.2.dist-info/top_level.txt
pylor-0.0.2.dist-info/RECORD
