Metadata-Version: 2.1
Name: pylor
Version: 0.0.2
Summary: Small package made for using ANSI codes
Home-page: https://github.com/MiranDaniel/pylor
Author: MiranDaniel
Author-email: mirandanielcz@gmail.com
License: UNKNOWN
Platform: UNKNOWN
Classifier: Programming Language :: Python :: 3
Classifier: License :: OSI Approved :: MIT License
Classifier: Operating System :: OS Independent
Requires-Python: >=3.6
